Metadata-Version: 2.1
Name: django-cas-mb
Version: 5.0.1
Summary: Django CAS 1.0/2.0/3.0 client authentication library, support Django 2.0, 2.1, 2.2, 3.0 and Python 3.5+
Home-page: https://github.com/mbenadda/django-cas-mb
Author: Mehdi Benadda (fork)
Author-email: me@mbenadda.com
License: MIT
Download-URL: https://github.com/django-cas-mb/django-cas-mb/releases
Keywords: django,cas,cas2,cas3,client,sso,single sign-on,Central Authentication Service,authentication,auth
Platform: UNKNOWN
Classifier: Development Status :: 5 - Production/Stable
Classifier: Environment :: Web Environment
Classifier: Framework :: Django
Classifier: Framework :: Django :: 2.0
Classifier: Framework :: Django :: 2.1
Classifier: Framework :: Django :: 2.2
Classifier: Framework :: Django :: 3.0
Classifier: Intended Audience :: Developers
Classifier: License :: OSI Approved :: MIT License
Classifier: Natural Language :: English
Classifier: Operating System :: OS Independent
Classifier: Programming Language :: Python
Classifier: Programming Language :: Python :: 3
Classifier: Programming Language :: Python :: 3 :: Only
Classifier: Programming Language :: Python :: 3.5
Classifier: Programming Language :: Python :: 3.6
Classifier: Programming Language :: Python :: 3.7
Classifier: Programming Language :: Python :: 3.8
Classifier: Topic :: Internet :: WWW/HTTP
Requires-Dist: Django (>=2.0)
Requires-Dist: python-cas-mb (>=1.5.1)
Provides-Extra: dev
Requires-Dist: black (==19.10b0) ; extra == 'dev'
Requires-Dist: twine (==3.1.1) ; extra == 'dev'
